learn_verilog/src/lab1/mux2to1_GL.v
module mux2to1_GL(a, b, sel, out);
    input a, b, sel;
    output out;
    wire selnot, a1, b1;
    not U1(selnot, sel);
    and U2(a1, a, selnot);
    and U3(b1, b, sel);
    or U4(out, a1, b1);
endmodule

learn_verilog/src/lab1/tb_1.v
`timescale 10ns/1ns
module testbench();
wire Rec;
reg SOut1, SOut2, SOut3;
mux2to1_GL u1(SOut1, SOut2, SOut3, Rec);

initial begin
    SOut1 = 0; SOut2 = 0; SOut3 = 0; // select a(SOut1)
#6  SOut1 = 0; SOut2 = 0; SOut3 = 1; // select b(SOut2)
#6  SOut1 = 1; SOut2 = 0; SOut3 = 0;
#6  SOut1 = 1; SOut2 = 0; SOut3 = 1;
#6  SOut1 = 0; SOut2 = 1; SOut3 = 0;
#6  SOut1 = 0; SOut2 = 1; SOut3 = 1;
#6  SOut1 = 1; SOut2 = 1; SOut3 = 0;
#6  SOut1 = 1; SOut2 = 1; SOut3 = 1;
#6  $finish;

end

initial begin
    $dumpfile("result.vcd");
    $dumpvars(0, testbench);
end

endmodule

learn_verilog/src/lab1/result.vcd
$date
	Thu Oct 31 19:55:13 2024
$end
$version
	Icarus Verilog
$end
$timescale
	1ns
$end
$scope module testbench $end
$var wire 1 ! Rec $end
$var reg 1 " SOut1 $end
$var reg 1 # SOut2 $end
$var reg 1 $ SOut3 $end
$scope module u1 $end
$var wire 1 " a $end
$var wire 1 % a1 $end
$var wire 1 # b $end
$var wire 1 & b1 $end
$var wire 1 ! out $end
$var wire 1 $ sel $end
$var wire 1 ' selnot $end
$upscope $end
$upscope $end
$enddefinitions $end
$comment Show the parameter values. $end
$dumpall
$end
#0
$dumpvars
1'
0&
0%
0$
0#
0"
0!
$end
#60
0'
1$
#120
1!
1%
1'
0$
1"
#180
0!
0%
0'
1$
#240
1'
0$
1#
0"
#300
1!
0'
1&
1$
#360
1%
1!
1'
0&
0$
1"
#420
0%
0'
1&
1$
